kb1000_discordpy_common/__init__.py
kb1000_discordpy_common/checks.py
kb1000_discordpy_common/help.py
kb1000_discordpy_common-1.3.dist-info/LICENSE
kb1000_discordpy_common-1.3.dist-info/METADATA
kb1000_discordpy_common-1.3.dist-info/WHEEL
kb1000_discordpy_common-1.3.dist-info/top_level.txt
kb1000_discordpy_common-1.3.dist-info/RECORD
