Metadata-Version: 2.1
Name: kb1000-discordpy-common
Version: 1.3
Summary: UNKNOWN
Home-page: https://github.com/kb-1000/kb1000_discordpy_common
Author: kb1000
Author-email: kaeptmblaubaer1000@gmail.com
License: Apache-2.0
Platform: UNKNOWN
Requires-Python: >=3.7.2
Requires-Dist: discord.py (>=1.5.1)
